testape/testape.py
testape-0.1.0.dist-info/METADATA
testape-0.1.0.dist-info/WHEEL
testape-0.1.0.dist-info/RECORD
