Metadata-Version: 2.1
Name: testape
Version: 0.1.0
Summary: SDK to create extsions for the Testape platform
Author: Lior Pollak
Author-email: 4294489+liorp@users.noreply.github.com
Requires-Python: >=3.10,<4.0
Classifier: Programming Language :: Python :: 3
Classifier: Programming Language :: Python :: 3.10
Classifier: Programming Language :: Python :: 3.11
